{
    "success": true,
    "result": {
        "PRODUCT": {
            "ID": "633990",
            "NAME": "Книга \"Адизес для лидеров\" | Ицхак Адизес",
            "IBLOCK_ID": "59",
            "IBLOCK_SECTION_ID": "4281",
            "DETAIL_PICTURE": "1824095",
            "DETAIL_TEXT": "",
            "DETAIL_PAGE_URL": "https://stage.05.ru/catalog/knigi_i_kanctovary/knigi/126505/",
            "CODE": "126505",
            "DETAIL_PAGE_PATH": "/catalog/knigi_i_kanctovary/knigi/126505/",
            "IMAGE": "https://img.stage.05.ru/resize/DkD-2d3emd2eF6cVAqMYN9HC2BtQq9SL2GrVEjFabXA//rs:fit:1197:1544:0:0/q:100/bG9jYWw6Ly8vdXBsb2FkL2libG9jay9hZmUvYWZlZTljODVhMmEwMDI2N2VhYTJmY2FhOWY1NTQyMTcuanBn",
            "PRICES": [
                {
                    "CODE": "DEFAULT",
                    "NAME": null,
                    "CROSSED": false,
                    "PRICE_TYPE_ID": 5,
                    "BONUS": 0,
                    "PRICE": 470,
                    "PRINT_PRICE": "470₽",
                    "CURRENCY": "RUB"
                },
                {
                    "CODE": "PROMO",
                    "NAME": null,
                    "CROSSED": true,
                    "PRICE_TYPE_ID": 9,
                    "BONUS": 0,
                    "PRICE": 530,
                    "PRINT_PRICE": "530₽",
                    "CURRENCY": "RUB"
                }
            ],
            "MAIN_PRICE": 530,
            "PRICE": 530,
            "IN_BASKET": false,
            "IN_FAVORITES": false,
            "IN_COMPARE": false,
            "DEFAULT_OFFERS": null,
            "ACTIONS": [
                {
                    "ID": 654738,
                    "NAME": "Развивайся с нами ",
                    "CODE": "razvivaysya_s_nami_",
                    "COLOR": "#4B0082"
                }
            ],
            "CUSTOM_SELLERS": null,
            "CREDIT_BUY_AVAILABILITY": false,
            "BRAND": {
                "ID": "257383",
                "UF_NAME": "Бомбора",
                "UF_XML_ID": "6d73a32a-afbe-11ea-bb9e-0cc47a5976ad",
                "UF_LINK": "bombora",
                "UF_FILE": "https://img.stage.05.ru/resize/GLuZeMOqByKILVk1JqG0MWrNg5yk_9gguDyk0h__I0s//rs:fit:300:225:0:0/q:100/bG9jYWw6Ly8vdXBsb2FkL3VmL2FmZS9hZmUyMjg0NDQyOWUyNTc5MDE1NWQ3MTM5ZGQwNWFiNi5qcGc",
                "UF_DESCRIPTION": "",
                "UF_FULL_DESCRIPTION": "",
                "IMAGE": "https://img.stage.05.ru/resize/GLuZeMOqByKILVk1JqG0MWrNg5yk_9gguDyk0h__I0s//rs:fit:300:225:0:0/q:100/bG9jYWw6Ly8vdXBsb2FkL3VmL2FmZS9hZmUyMjg0NDQyOWUyNTc5MDE1NWQ3MTM5ZGQwNWFiNi5qcGc",
                "THUMBNAILS": {
                    "1X": "https://img.stage.05.ru/resize/QMQYxvBKFYt8hh5nOj22vb4NwmRiPVabHjV3iIjGAYs//rs:fit:250:250:0:0/q:100/bG9jYWw6Ly8vdXBsb2FkL3VmL2FmZS9hZmUyMjg0NDQyOWUyNTc5MDE1NWQ3MTM5ZGQwNWFiNi5qcGc",
                    "2X": "https://img.stage.05.ru/resize/bfvFjBf4Od83tJITQyqw-ON5AaEcah4_UeLHbxrvIqc//rs:fit:500:500:0:0/q:100/bG9jYWw6Ly8vdXBsb2FkL3VmL2FmZS9hZmUyMjg0NDQyOWUyNTc5MDE1NWQ3MTM5ZGQwNWFiNi5qcGc"
                },
                "NAME": "Бомбора",
                "CODE": "bombora",
                "DESCRIPTION": null,
                "FULL_DESCRIPTION": null,
                "DETAIL_PAGE_PATH": "https://stage.05.ru/brands/bombora",
                "DETAIL_PAGE_URL": "https://stage.05.ru/brands/bombora"
            },
            "SECTION": "Книги",
            "IS_PRODUCT_IN_FAVORITES": false,
            "META": {
                "ELEMENT_META_TITLE": "Книга &quot;Адизес для лидеров&quot; | Ицхак Адизес - купить в 05.RU, цены, отзывы",
                "ELEMENT_META_DESCRIPTION": "Купить Книга &quot;Адизес для лидеров&quot; | Ицхак Адизес по доступным ценам в интернет-магазине 05.RU. Книга &quot;Адизес для лидеров&quot; | Ицхак Адизес - аксессуары, отзывы, цены и фото. Заказать можно на сайте или по телефону +7 (8722) 51-51-51",
                "SECTION_META_TITLE": "Книга &quot;Адизес для лидеров&quot; | Ицхак Адизес —  Купить в интернет-магазине 05.RU по низкой цене",
                "SECTION_META_DESCRIPTION": "Отличные цены на товары из раздела &quot;Книга &quot;Адизес для лидеров&quot; | Ицхак Адизес&quot; в интернет-магазине 05.RU ✔  В каталоге &quot;Книга &quot;Адизес для лидеров&quot; | Ицхак Адизес&quot; можно ознакомиться с ценами, фотографиями и подробными характеристиками "
            },
            "STATUS": {
                "DEFAULT": 5,
                "NAME": "мало",
                "DESCRIPTION_PART": "Осталось",
                "ICON": false,
                "TEXT": "Осталось мало",
                "COLOR": "#E23512",
                "CODE": "FEW",
                "CLASS": "bem-pseudo_red",
                "FREE_DELIVERY": false
            },
            "FREE_DELIVERY": false,
            "ADDITIONAL": {
                "STATUS": {
                    "DEFAULT": 5,
                    "NAME": "мало",
                    "DESCRIPTION_PART": "Осталось",
                    "ICON": false,
                    "TEXT": "Осталось мало",
                    "COLOR": "#E23512",
                    "CODE": "FEW",
                    "CLASS": "bem-pseudo_red",
                    "FREE_DELIVERY": false
                },
                "FREE_DELIVERY": false,
                "DELIVERIES": {
                    "NAME": "Способы доставки",
                    "PHOTO": "http://stage.05.ru/images/app/png/product-info-block__icon-delivery.png",
                    "IMAGE": "http://stage.05.ru/images/app/png/product-info-block__icon-delivery.png",
                    "AMOUNT": null,
                    "COLOR": null,
                    "ITEMS": [
                        {
                            "NAME": "Курьерская доставка 05.ru",
                            "PRICE": 100,
                            "PRICE_FORMATED": "100₽",
                            "PERIOD_TEXT": "сегодня",
                            "IS_SELFDELIVERY": "N",
                            "DESCRIPTION": "Курьерская доставка 05.ru",
                            "VALUE": "100₽",
                            "STORE_LIST": [],
                            "SELLERS": null
                        },
                        {
                            "NAME": "Самовывоз",
                            "PRICE": 0,
                            "PRICE_FORMATED": "бесплатно",
                            "PERIOD_TEXT": "сегодня",
                            "IS_SELFDELIVERY": "Y",
                            "DESCRIPTION": "Забрать заказ в нашем магазине по адресу пр.Шамиля, 5/ пр.Шамиля 31г",
                            "VALUE": "бесплатно",
                            "STORE_LIST": [
                                "254",
                                "233",
                                "245"
                            ],
                            "SELLERS": null
                        }
                    ]
                },
                "PAYMENTS": {
                    "NAME": "Способы оплаты",
                    "PHOTO": "http://stage.05.ru/images/app/png/card.png",
                    "IMAGE": "http://stage.05.ru/images/app/png/card.png",
                    "AMOUNT": null,
                    "COLOR": null,
                    "ITEMS": [
                        {
                            "NAME": "Наличными при получении",
                            "DESCRIPTION": "Оплата наличными при получении заказа курьеру."
                        },
                        {
                            "NAME": "Сбербанк.QR",
                            "DESCRIPTION": ""
                        }
                    ]
                },
                "REMAINS": {
                    "NAME": "Осталось",
                    "IMAGE": null,
                    "AMOUNT": {
                        "COLOR": "#E23512",
                        "VALUE": "мало"
                    },
                    "COLOR": "#E23512",
                    "ITEMS": [
                        {
                            "PRODUCT_ID": "633990",
                            "AMOUNT": "1",
                            "STORE_ID": "254",
                            "QUANTITY": "1",
                            "TITLE": "Махачкала, пр-кт И. Шамиля, 31г",
                            "IMAGE": null,
                            "ADDRESS": "пр-кт И. Шамиля, 31г",
                            "IS_MARKETPLACE": "0",
                            "MP_DELIVERY_DAYS": "0",
                            "XML_ID": "6e31745d-ff94-11e9-bb9d-0cc47a5976ac",
                            "QUANTITY_STATUS_CODE": "FEW",
                            "QUANTITY_STATUS": "мало",
                            "COLOR": "#E23512",
                            "NAME": "Махачкала, пр-кт И. Шамиля, 31г",
                            "VALUE": "мало",
                            "IS_CURRENT": true
                        }
                    ]
                },
                "INSTALLMENT": {
                    "NAME": "Рассрочка от 133₽",
                    "PHOTO": "http://stage.05.ru/images/app/png/product-info-block__icon-ruble.png",
                    "IMAGE": "http://stage.05.ru/images/app/png/product-info-block__icon-ruble.png",
                    "ITEMS": [
                        {
                            "PARAM": "period",
                            "CURRENT_VALUE_INDEX": 5,
                            "NAME": "Срок",
                            "ITEMS": [
                                {
                                    "NAME": "1 мес.",
                                    "VALUE": 1
                                },
                                {
                                    "NAME": "2 мес.",
                                    "VALUE": 2
                                },
                                {
                                    "NAME": "3 мес.",
                                    "VALUE": 3
                                },
                                {
                                    "NAME": "4 мес.",
                                    "VALUE": 4
                                },
                                {
                                    "NAME": "5 мес.",
                                    "VALUE": 5
                                },
                                {
                                    "NAME": "6 мес.",
                                    "VALUE": 6
                                }
                            ]
                        },
                        {
                            "PARAM": "guarantors",
                            "CURRENT_VALUE_INDEX": 0,
                            "NAME": "Поручителей",
                            "ITEMS": [
                                {
                                    "NAME": "Нет",
                                    "VALUE": 0
                                },
                                {
                                    "NAME": 1,
                                    "VALUE": 1
                                }
                            ]
                        },
                        {
                            "NAME": "Первый взнос",
                            "VALUE": "133₽"
                        },
                        {
                            "NAME": "Переплата",
                            "VALUE": "137₽"
                        },
                        {
                            "NAME": "Ежемесячный платёж",
                            "VALUE": "90₽"
                        },
                        {
                            "NAME": "Итоговая сумма",
                            "VALUE": "667₽"
                        }
                    ]
                }
            },
            "DELIVERIES": {
                "NAME": "Способы доставки",
                "PHOTO": "http://stage.05.ru/images/app/png/product-info-block__icon-delivery.png",
                "IMAGE": "http://stage.05.ru/images/app/png/product-info-block__icon-delivery.png",
                "AMOUNT": null,
                "COLOR": null,
                "ITEMS": [
                    {
                        "NAME": "Курьерская доставка 05.ru",
                        "PRICE": 100,
                        "PRICE_FORMATED": "100₽",
                        "PERIOD_TEXT": "сегодня",
                        "IS_SELFDELIVERY": "N",
                        "DESCRIPTION": "Курьерская доставка 05.ru",
                        "VALUE": "100₽",
                        "STORE_LIST": [],
                        "SELLERS": null
                    },
                    {
                        "NAME": "Самовывоз",
                        "PRICE": 0,
                        "PRICE_FORMATED": "бесплатно",
                        "PERIOD_TEXT": "сегодня",
                        "IS_SELFDELIVERY": "Y",
                        "DESCRIPTION": "Забрать заказ в нашем магазине по адресу пр.Шамиля, 5/ пр.Шамиля 31г",
                        "VALUE": "бесплатно",
                        "STORE_LIST": [
                            "254",
                            "233",
                            "245"
                        ],
                        "SELLERS": null
                    }
                ]
            },
            "PAYMENTS": {
                "NAME": "Способы оплаты",
                "PHOTO": "http://stage.05.ru/images/app/png/card.png",
                "IMAGE": "http://stage.05.ru/images/app/png/card.png",
                "AMOUNT": null,
                "COLOR": null,
                "ITEMS": [
                    {
                        "NAME": "Наличными при получении",
                        "DESCRIPTION": "Оплата наличными при получении заказа курьеру."
                    },
                    {
                        "NAME": "Сбербанк.QR",
                        "DESCRIPTION": ""
                    }
                ]
            },
            "INSTALLMENT": {
                "NAME": "Рассрочка от 133₽",
                "PHOTO": "http://stage.05.ru/images/app/png/product-info-block__icon-ruble.png",
                "IMAGE": "http://stage.05.ru/images/app/png/product-info-block__icon-ruble.png",
                "ITEMS": [
                    {
                        "PARAM": "period",
                        "CURRENT_VALUE_INDEX": 5,
                        "NAME": "Срок",
                        "ITEMS": [
                            {
                                "NAME": "1 мес.",
                                "VALUE": 1
                            },
                            {
                                "NAME": "2 мес.",
                                "VALUE": 2
                            },
                            {
                                "NAME": "3 мес.",
                                "VALUE": 3
                            },
                            {
                                "NAME": "4 мес.",
                                "VALUE": 4
                            },
                            {
                                "NAME": "5 мес.",
                                "VALUE": 5
                            },
                            {
                                "NAME": "6 мес.",
                                "VALUE": 6
                            }
                        ]
                    },
                    {
                        "PARAM": "guarantors",
                        "CURRENT_VALUE_INDEX": 0,
                        "NAME": "Поручителей",
                        "ITEMS": [
                            {
                                "NAME": "Нет",
                                "VALUE": 0
                            },
                            {
                                "NAME": 1,
                                "VALUE": 1
                            }
                        ]
                    },
                    {
                        "NAME": "Первый взнос",
                        "VALUE": "133₽"
                    },
                    {
                        "NAME": "Переплата",
                        "VALUE": "137₽"
                    },
                    {
                        "NAME": "Ежемесячный платёж",
                        "VALUE": "90₽"
                    },
                    {
                        "NAME": "Итоговая сумма",
                        "VALUE": "667₽"
                    }
                ]
            },
            "ACCESSORIES": null,
            "MORE_PHOTO": [],
            "IMAGES": [],
            "APPEAL_TYPES": [
                {
                    "ID": "1",
                    "NAME": "Жалоба"
                },
                {
                    "ID": "2",
                    "NAME": "Отзыв"
                },
                {
                    "ID": "3",
                    "NAME": "Пожелание"
                },
                {
                    "ID": "9",
                    "NAME": "Узнать цену"
                },
                {
                    "ID": "10",
                    "NAME": "Консультация"
                },
                {
                    "ID": "11",
                    "NAME": "Гарантийное обслуживание"
                },
                {
                    "ID": "12",
                    "NAME": "Хочу сделать заказ"
                },
                {
                    "ID": "13",
                    "NAME": "Оффлайн сообщение с jivosite"
                },
                {
                    "ID": "15",
                    "NAME": "Нашли дешевле"
                },
                {
                    "ID": "16",
                    "NAME": "Обратный звонок из телеграма"
                },
                {
                    "ID": "17",
                    "NAME": "Отзыв из телеграма"
                },
                {
                    "ID": "18",
                    "NAME": "Китайский понедельник"
                },
                {
                    "ID": "23",
                    "NAME": "Проблема с активацией бонусной карты"
                },
                {
                    "ID": "24",
                    "NAME": "Не нашли, что искали?"
                },
                {
                    "ID": "57",
                    "NAME": "Заявка на рассрочку"
                }
            ],
            "PROPERTIES": [
                {
                    "GROUP_NAME": "",
                    "PROPERTIES": {
                        "Жанры/тематика": "деловой бестселлер",
                        "Год выпуска": "2017",
                        "Возрастные ограничения": "16+",
                        "Обложка": "твердая",
                        "Автор": "Ицхак Адизес",
                        "Количество страниц": "280",
                        "Описание": "На протяжении нескольких лет всемирно известный коуч Ицхак Адизес общался с президентами компаний, которые когда-то обратились к нему за помощью: о том, как методология Адизеса помогла им, о секретах лидерства и о том, что изменилось за последние годы."
                    }
                }
            ],
            "MAIN_PROPERTIES": [
                {
                    "NAME": "Артикул",
                    "CODE": "CML2_ARTICLE",
                    "ID": "51409",
                    "VALUE": "05 АДЛИА",
                    "TYPE": null,
                    "HTML_NAME": "prop_51409",
                    "HTML_VALUE": "05+%D0%90%D0%94%D0%9B%D0%98%D0%90"
                },
                {
                    "NAME": "Производитель",
                    "CODE": "CML2_BRANDS_REF",
                    "ID": "257383",
                    "VALUE": "Бомбора",
                    "TYPE": "BRAND",
                    "HTML_NAME": "prop_3492",
                    "HTML_VALUE": "%D0%91%D0%BE%D0%BC%D0%B1%D0%BE%D1%80%D0%B0"
                },
                {
                    "NAME": "Код товара",
                    "CODE": "CML2_CODE",
                    "ID": "50959",
                    "VALUE": "126505",
                    "TYPE": "CODE",
                    "HTML_NAME": "prop_50959",
                    "HTML_VALUE": "126505"
                },
                {
                    "NAME": "Гарантийный срок",
                    "CODE": "CML2_GARANT",
                    "ID": "48365",
                    "VALUE": "",
                    "TYPE": null,
                    "HTML_NAME": "prop_48365",
                    "HTML_VALUE": ""
                }
            ],
            "OFFERS": null,
            "SECTION_NAV_CHAIN": [
                {
                    "ID": "4722",
                    "NAME": "Книги и канцтовары",
                    "CODE": "knigi_i_kanctovary",
                    "UPDATED": "2021-03-29",
                    "LEFT_MARGIN": "1243",
                    "RIGHT_MARGIN": "1308",
                    "UF_CAT_LIST": null,
                    "PARENT_ID": null,
                    "PARENT_NAME": null,
                    "SECTION_PAGE_PATH": "/catalog/knigi_i_kanctovary/",
                    "IMAGE": "https://img.stage.05.ru/resize/kVGoAbRlIwPIX7pzAUgMGHd36vHHvXlEDIOiJmDaloc//rs:fit:1062:1600:0:0/q:100/bG9jYWw6Ly8vdXBsb2FkL2libG9jay85ZDcvOWQ3OGIzYWU2MDQ1MjIyZGJkYzRlMGYzOGYxOTAzYzQuanBn",
                    "ICON": null,
                    "THUMBNAILS": {
                        "1X": "https://img.stage.05.ru/resize/xw7VxACb4BeWrx9DXSKQo7Nq-fNqSSkTr_ENNKWvGwc//rs:fit:50:50:0:0/q:100/bG9jYWw6Ly8vdXBsb2FkL2libG9jay85ZDcvOWQ3OGIzYWU2MDQ1MjIyZGJkYzRlMGYzOGYxOTAzYzQuanBn",
                        "2X": "https://img.stage.05.ru/resize/l24Ou79eK1YtojFNqk8uBLlT4Cca53IMQIUxDn_AaVM//rs:fit:100:100:0:0/q:100/bG9jYWw6Ly8vdXBsb2FkL2libG9jay85ZDcvOWQ3OGIzYWU2MDQ1MjIyZGJkYzRlMGYzOGYxOTAzYzQuanBn"
                    },
                    "LINK": {
                        "TYPE": "CATALOG",
                        "VALUE": "4722"
                    },
                    "CHILDREN": [
                        {
                            "ID": "4281",
                            "NAME": "Книги",
                            "CODE": "knigi",
                            "UPDATED": "2021-03-19",
                            "LEFT_MARGIN": "1300",
                            "RIGHT_MARGIN": "1303",
                            "UF_CAT_LIST": null,
                            "PARENT_ID": "4722",
                            "PARENT_NAME": "Книги и канцтовары",
                            "SECTION_PAGE_PATH": "/catalog/knigi_i_kanctovary/knigi/",
                            "IMAGE": "https://img.stage.05.ru/resize/XkA-vtO__YNsJ5OAtbbPEi6Wn141jQ2dMCalcRtFyLE//rs:fit:1051:1500:0:0/q:100/bG9jYWw6Ly8vdXBsb2FkL2libG9jay9hYzgvYWM4MjcwZTZhODc3YzBkNGE3YmI2OGY4NjhkY2VlOGMuanBn",
                            "ICON": null,
                            "THUMBNAILS": {
                                "1X": "https://img.stage.05.ru/resize/IhaAiizlBeLrDuIyXlLkRJOsvG8V64o8bjy0qFxTN7Y//rs:fit:50:50:0:0/q:100/bG9jYWw6Ly8vdXBsb2FkL2libG9jay9hYzgvYWM4MjcwZTZhODc3YzBkNGE3YmI2OGY4NjhkY2VlOGMuanBn",
                                "2X": "https://img.stage.05.ru/resize/9qFVPeqyABz9UQEQjuL2v0AjqADURvvbP1RMVuA3oGg//rs:fit:100:100:0:0/q:100/bG9jYWw6Ly8vdXBsb2FkL2libG9jay9hYzgvYWM4MjcwZTZhODc3YzBkNGE3YmI2OGY4NjhkY2VlOGMuanBn"
                            },
                            "LINK": {
                                "TYPE": "CATALOG",
                                "VALUE": "4281"
                            }
                        }
                    ]
                }
            ],
            "ADDITIONAL_PRODUCTS": [
                {
                    "GROUP_NAME": "Похожие товары",
                    "ITEMS": [
                        {
                            "ID": "608773",
                            "NAME": "Книга \"Магия Утра\" | Хэл Элрод",
                            "DETAIL_PAGE_PATH": "/catalog/knigi_i_kanctovary/knigi/104404/",
                            "IMAGE": "https://img.stage.05.ru/resize/5sdpA9YsjR57I9jAQSSlRmLa5bmkdcf31HiF345gfMg//rs:fit:1200:1745:0:0/q:100/bG9jYWw6Ly8vdXBsb2FkL2libG9jay9iNmQvYjZkYWJkMzMzN2JmMjQwM2FiZDI0MWFlMjkxMzYwYzIuanBn",
                            "THUMBNAILS": {
                                "1X": "https://img.stage.05.ru/resize/SidcOdtwZ3eupbTVkUBotZCjGRBi8cCECKTYY4XCCLY//rs:fit:250:250:0:0/q:100/bG9jYWw6Ly8vdXBsb2FkL2libG9jay9iNmQvYjZkYWJkMzMzN2JmMjQwM2FiZDI0MWFlMjkxMzYwYzIuanBn",
                                "2X": "https://img.stage.05.ru/resize/h2saDZgqm3Hspx3CmjPOW1zHA9a-440Vmwnsl563Ob0//rs:fit:500:500:0:0/q:100/bG9jYWw6Ly8vdXBsb2FkL2libG9jay9iNmQvYjZkYWJkMzMzN2JmMjQwM2FiZDI0MWFlMjkxMzYwYzIuanBn"
                            },
                            "PRICES": [
                                {
                                    "CODE": "DEFAULT",
                                    "NAME": null,
                                    "CROSSED": false,
                                    "PRICE_TYPE_ID": 5,
                                    "BONUS": 0,
                                    "PRICE": 620,
                                    "PRINT_PRICE": "620₽",
                                    "CURRENCY": "RUB"
                                }
                            ],
                            "PRICE": 620,
                            "PRINT_PRICE": "620₽",
                            "ACTIONS": [
                                {
                                    "ID": 654738,
                                    "NAME": "Развивайся с нами ",
                                    "CODE": "razvivaysya_s_nami_",
                                    "COLOR": "#4B0082"
                                }
                            ]
                        },
                        {
                            "ID": "608774",
                            "NAME": "Книга \"НЕ ТУПИ\" | Джен Синсеро",
                            "DETAIL_PAGE_PATH": "/catalog/knigi_i_kanctovary/knigi/104402/",
                            "IMAGE": "https://img.stage.05.ru/resize/fPFlTvSFrzQiZRXsLYagcYrpRwSqygbIKhIc6-gHM_k//rs:fit:555:795:0:0/q:100/bG9jYWw6Ly8vdXBsb2FkL2libG9jay9hMGUvYTBlMThjNGRhMTZkY2E0MWFlYzY2ODk1ZDY4MzMzZWUuanBn",
                            "THUMBNAILS": {
                                "1X": "https://img.stage.05.ru/resize/61-auKyQ99eWA4FsFe4dCNQN9tfv7MEWppdKA0islho//rs:fit:250:250:0:0/q:100/bG9jYWw6Ly8vdXBsb2FkL2libG9jay9hMGUvYTBlMThjNGRhMTZkY2E0MWFlYzY2ODk1ZDY4MzMzZWUuanBn",
                                "2X": "https://img.stage.05.ru/resize/dhtNaofPbhi94s5nEwYwOMSKzxEqCne8jfYAJUY-8fo//rs:fit:500:500:0:0/q:100/bG9jYWw6Ly8vdXBsb2FkL2libG9jay9hMGUvYTBlMThjNGRhMTZkY2E0MWFlYzY2ODk1ZDY4MzMzZWUuanBn"
                            },
                            "PRICES": [
                                {
                                    "CODE": "DEFAULT",
                                    "NAME": null,
                                    "CROSSED": false,
                                    "PRICE_TYPE_ID": 5,
                                    "BONUS": 0,
                                    "PRICE": 500,
                                    "PRINT_PRICE": "500₽",
                                    "CURRENCY": "RUB"
                                }
                            ],
                            "PRICE": 500,
                            "PRINT_PRICE": "500₽",
                            "ACTIONS": [
                                {
                                    "ID": 654738,
                                    "NAME": "Развивайся с нами ",
                                    "CODE": "razvivaysya_s_nami_",
                                    "COLOR": "#4B0082"
                                }
                            ]
                        },
                        {
                            "ID": "608775",
                            "NAME": "Книга \"Между надо и хочу\" |  Эль Луна",
                            "DETAIL_PAGE_PATH": "/catalog/knigi_i_kanctovary/knigi/104413/",
                            "IMAGE": "https://img.stage.05.ru/resize/HmSFZ4MZQOzpLYKn2vqFtawwY0jYYOcSq8N4pD7HCss//rs:fit:1056:1500:0:0/q:100/bG9jYWw6Ly8vdXBsb2FkL2libG9jay85ODcvOTg3ZTQwOTljYWI4Mjk1MDUxYTg1NmNiZTViYTljYmIuanBn",
                            "THUMBNAILS": {
                                "1X": "https://img.stage.05.ru/resize/j5OW8mcIbW5ZGOgH5K9UV4CcQK_p8ksREE8QiOKqVaE//rs:fit:250:250:0:0/q:100/bG9jYWw6Ly8vdXBsb2FkL2libG9jay85ODcvOTg3ZTQwOTljYWI4Mjk1MDUxYTg1NmNiZTViYTljYmIuanBn",
                                "2X": "https://img.stage.05.ru/resize/ZFJwjHQukdv0VIU-3MmtQCqOQIOHd6zCui8CMSvEQfw//rs:fit:500:500:0:0/q:100/bG9jYWw6Ly8vdXBsb2FkL2libG9jay85ODcvOTg3ZTQwOTljYWI4Mjk1MDUxYTg1NmNiZTViYTljYmIuanBn"
                            },
                            "PRICES": [
                                {
                                    "CODE": "DEFAULT",
                                    "NAME": null,
                                    "CROSSED": false,
                                    "PRICE_TYPE_ID": 5,
                                    "BONUS": 0,
                                    "PRICE": 610,
                                    "PRINT_PRICE": "610₽",
                                    "CURRENCY": "RUB"
                                },
                                {
                                    "CODE": "PROMO",
                                    "NAME": null,
                                    "CROSSED": true,
                                    "PRICE_TYPE_ID": 9,
                                    "BONUS": 0,
                                    "PRICE": 720,
                                    "PRINT_PRICE": "720₽",
                                    "CURRENCY": "RUB"
                                }
                            ],
                            "PRICE": 720,
                            "PRINT_PRICE": "720₽",
                            "ACTIONS": [
                                {
                                    "ID": 654738,
                                    "NAME": "Развивайся с нами ",
                                    "CODE": "razvivaysya_s_nami_",
                                    "COLOR": "#4B0082"
                                }
                            ]
                        },
                        {
                            "ID": "608791",
                            "NAME": "Книга \"Выйди из зоны комфорта\" | Брайан Трейси",
                            "DETAIL_PAGE_PATH": "/catalog/knigi_i_kanctovary/knigi/104387/",
                            "IMAGE": "https://img.stage.05.ru/resize/adp50Onfy-SLLiQdVXHlwR1fCysFbkBYG2ISWTiikCw//rs:fit:475:537:0:0/q:100/bG9jYWw6Ly8vdXBsb2FkL2libG9jay84YmIvOGJiMDQ2ZTA4ZTkyNGUwMjg0YjY2NjM1NGQyMTNmMmEuanBn",
                            "THUMBNAILS": {
                                "1X": "https://img.stage.05.ru/resize/tf3X9yCmtM3ooXj35huIwdYwgmHpodfIFvLiRau6dcY//rs:fit:250:250:0:0/q:100/bG9jYWw6Ly8vdXBsb2FkL2libG9jay84YmIvOGJiMDQ2ZTA4ZTkyNGUwMjg0YjY2NjM1NGQyMTNmMmEuanBn",
                                "2X": "https://img.stage.05.ru/resize/qf1nfmg7D74TGSzzIMOWNmOND2-GaDZJ6gen5A-E6as//rs:fit:500:500:0:0/q:100/bG9jYWw6Ly8vdXBsb2FkL2libG9jay84YmIvOGJiMDQ2ZTA4ZTkyNGUwMjg0YjY2NjM1NGQyMTNmMmEuanBn"
                            },
                            "PRICES": [
                                {
                                    "CODE": "DEFAULT",
                                    "NAME": null,
                                    "CROSSED": false,
                                    "PRICE_TYPE_ID": 5,
                                    "BONUS": 0,
                                    "PRICE": 580,
                                    "PRINT_PRICE": "580₽",
                                    "CURRENCY": "RUB"
                                },
                                {
                                    "CODE": "PROMO",
                                    "NAME": null,
                                    "CROSSED": true,
                                    "PRICE_TYPE_ID": 9,
                                    "BONUS": 0,
                                    "PRICE": 660,
                                    "PRINT_PRICE": "660₽",
                                    "CURRENCY": "RUB"
                                }
                            ],
                            "PRICE": 660,
                            "PRINT_PRICE": "660₽",
                            "ACTIONS": [
                                {
                                    "ID": 654738,
                                    "NAME": "Развивайся с нами ",
                                    "CODE": "razvivaysya_s_nami_",
                                    "COLOR": "#4B0082"
                                }
                            ]
                        },
                        {
                            "ID": "608857",
                            "NAME": "Книга \"Не работайте с мудаками\" | Роберт Саттон",
                            "DETAIL_PAGE_PATH": "/catalog/knigi_i_kanctovary/knigi/104395/",
                            "IMAGE": "https://img.stage.05.ru/resize/ciXJD9nQ8cPZBsWqUAg5U6kXx1qNTI84aq_XvVts2Og//rs:fit:900:1200:0:0/q:100/bG9jYWw6Ly8vdXBsb2FkL2libG9jay9iNTcvYjU3ZDRlMjI0YTBlMTk5NzdiNjQ2ZGYyYzE0ODdlMDkuanBn",
                            "THUMBNAILS": {
                                "1X": "https://img.stage.05.ru/resize/JO6zG6y8pKv1k92c6AVk3saKOoDRLFBibfxLbv_U1ZY//rs:fit:250:250:0:0/q:100/bG9jYWw6Ly8vdXBsb2FkL2libG9jay9iNTcvYjU3ZDRlMjI0YTBlMTk5NzdiNjQ2ZGYyYzE0ODdlMDkuanBn",
                                "2X": "https://img.stage.05.ru/resize/TrnDi_ighsI9fMYOcdaHiFLu_WsPer_uuCyv6utUgAE//rs:fit:500:500:0:0/q:100/bG9jYWw6Ly8vdXBsb2FkL2libG9jay9iNTcvYjU3ZDRlMjI0YTBlMTk5NzdiNjQ2ZGYyYzE0ODdlMDkuanBn"
                            },
                            "PRICES": [
                                {
                                    "CODE": "DEFAULT",
                                    "NAME": null,
                                    "CROSSED": false,
                                    "PRICE_TYPE_ID": 5,
                                    "BONUS": 0,
                                    "PRICE": 590,
                                    "PRINT_PRICE": "590₽",
                                    "CURRENCY": "RUB"
                                },
                                {
                                    "CODE": "PROMO",
                                    "NAME": null,
                                    "CROSSED": true,
                                    "PRICE_TYPE_ID": 9,
                                    "BONUS": 0,
                                    "PRICE": 650,
                                    "PRINT_PRICE": "650₽",
                                    "CURRENCY": "RUB"
                                }
                            ],
                            "PRICE": 650,
                            "PRINT_PRICE": "650₽",
                            "ACTIONS": [
                                {
                                    "ID": 654738,
                                    "NAME": "Развивайся с нами ",
                                    "CODE": "razvivaysya_s_nami_",
                                    "COLOR": "#4B0082"
                                }
                            ]
                        },
                        {
                            "ID": "608873",
                            "NAME": "Книга \"SCRUM Революционный метод управления проектами\" | Джефф Сазерленд",
                            "DETAIL_PAGE_PATH": "/catalog/knigi_i_kanctovary/knigi/104405/",
                            "IMAGE": "https://img.stage.05.ru/resize/B30AOtO_04AlapAoz_53Amnt8Y94AV65b5Fza3HMpNo//rs:fit:927:1334:0:0/q:100/bG9jYWw6Ly8vdXBsb2FkL2libG9jay9iNmYvYjZmNDgyMWNkZjZjZWQ2ZmJmM2MyZTFmMzk2MGE0MTguanBn",
                            "THUMBNAILS": {
                                "1X": "https://img.stage.05.ru/resize/IyXw-5tqDmWS8jl1unHpY2myZjzxYFoEJAe4zrJNdCc//rs:fit:250:250:0:0/q:100/bG9jYWw6Ly8vdXBsb2FkL2libG9jay9iNmYvYjZmNDgyMWNkZjZjZWQ2ZmJmM2MyZTFmMzk2MGE0MTguanBn",
                                "2X": "https://img.stage.05.ru/resize/jTu7lO4roeok3SXIeGdjxdM2CNfiIEwZQHCXB5MDdJg//rs:fit:500:500:0:0/q:100/bG9jYWw6Ly8vdXBsb2FkL2libG9jay9iNmYvYjZmNDgyMWNkZjZjZWQ2ZmJmM2MyZTFmMzk2MGE0MTguanBn"
                            },
                            "PRICES": [
                                {
                                    "CODE": "DEFAULT",
                                    "NAME": null,
                                    "CROSSED": false,
                                    "PRICE_TYPE_ID": 5,
                                    "BONUS": 0,
                                    "PRICE": 605,
                                    "PRINT_PRICE": "605₽",
                                    "CURRENCY": "RUB"
                                },
                                {
                                    "CODE": "PROMO",
                                    "NAME": null,
                                    "CROSSED": true,
                                    "PRICE_TYPE_ID": 9,
                                    "BONUS": 0,
                                    "PRICE": 670,
                                    "PRINT_PRICE": "670₽",
                                    "CURRENCY": "RUB"
                                }
                            ],
                            "PRICE": 670,
                            "PRINT_PRICE": "670₽",
                            "ACTIONS": [
                                {
                                    "ID": 654738,
                                    "NAME": "Развивайся с нами ",
                                    "CODE": "razvivaysya_s_nami_",
                                    "COLOR": "#4B0082"
                                }
                            ]
                        },
                        {
                            "ID": "608891",
                            "NAME": "Книга \"Скорочтение\" | Питер Камп",
                            "DETAIL_PAGE_PATH": "/catalog/knigi_i_kanctovary/knigi/104379/",
                            "IMAGE": "https://img.stage.05.ru/resize/GsOFxmqsiloTbjQD3PvMmAteux6TsDII6BD1lsU33B0//rs:fit:379:501:0:0/q:100/bG9jYWw6Ly8vdXBsb2FkL2libG9jay83NTYvNzU2ZDk0MWFlNmY0NzBiNzViMjA2NWZiMTgwNzc0NWUuanBn",
                            "THUMBNAILS": {
                                "1X": "https://img.stage.05.ru/resize/PbdMM_40KTS16qFTIXp5i1bepB7A1Kd8fdjwLeryPXU//rs:fit:250:250:0:0/q:100/bG9jYWw6Ly8vdXBsb2FkL2libG9jay83NTYvNzU2ZDk0MWFlNmY0NzBiNzViMjA2NWZiMTgwNzc0NWUuanBn",
                                "2X": "https://img.stage.05.ru/resize/Hopg7vvZbQO0gTdQ5GSxotXpCYbN0ht7M1dQ-cOIz8U//rs:fit:500:500:0:0/q:100/bG9jYWw6Ly8vdXBsb2FkL2libG9jay83NTYvNzU2ZDk0MWFlNmY0NzBiNzViMjA2NWZiMTgwNzc0NWUuanBn"
                            },
                            "PRICES": [
                                {
                                    "CODE": "DEFAULT",
                                    "NAME": null,
                                    "CROSSED": false,
                                    "PRICE_TYPE_ID": 5,
                                    "BONUS": 0,
                                    "PRICE": 630,
                                    "PRINT_PRICE": "630₽",
                                    "CURRENCY": "RUB"
                                }
                            ],
                            "PRICE": 630,
                            "PRINT_PRICE": "630₽",
                            "ACTIONS": [
                                {
                                    "ID": 654738,
                                    "NAME": "Развивайся с нами ",
                                    "CODE": "razvivaysya_s_nami_",
                                    "COLOR": "#4B0082"
                                }
                            ]
                        },
                        {
                            "ID": "608903",
                            "NAME": "Книга \"Феномен ZARA\" | О`Ши Ковадонга",
                            "DETAIL_PAGE_PATH": "/catalog/knigi_i_kanctovary/knigi/104343/",
                            "IMAGE": "https://img.stage.05.ru/resize/fnE8EYawqEL0Jaq6eJ-Tb2d3TgBRi0wj0DF4e1Khe7k//rs:fit:301:500:0:0/q:100/bG9jYWw6Ly8vdXBsb2FkL2libG9jay81MDIvNTAyZTIzMGQ1ZTBkODBlZmE5NDQwNjU3NjdhYTQxMzUuanBn",
                            "THUMBNAILS": {
                                "1X": "https://img.stage.05.ru/resize/DAIuMvKN1jXt1J_RqKtpoCB9MI1ZDkfRAPGfY90dmrc//rs:fit:250:250:0:0/q:100/bG9jYWw6Ly8vdXBsb2FkL2libG9jay81MDIvNTAyZTIzMGQ1ZTBkODBlZmE5NDQwNjU3NjdhYTQxMzUuanBn",
                                "2X": "https://img.stage.05.ru/resize/gtqQk4gw_jb3XptSI3nFQAASBU4hHp4Ec7lyfhJC-xg//rs:fit:500:500:0:0/q:100/bG9jYWw6Ly8vdXBsb2FkL2libG9jay81MDIvNTAyZTIzMGQ1ZTBkODBlZmE5NDQwNjU3NjdhYTQxMzUuanBn"
                            },
                            "PRICES": [
                                {
                                    "CODE": "DEFAULT",
                                    "NAME": null,
                                    "CROSSED": false,
                                    "PRICE_TYPE_ID": 5,
                                    "BONUS": 0,
                                    "PRICE": 485,
                                    "PRINT_PRICE": "485₽",
                                    "CURRENCY": "RUB"
                                },
                                {
                                    "CODE": "PROMO",
                                    "NAME": null,
                                    "CROSSED": true,
                                    "PRICE_TYPE_ID": 9,
                                    "BONUS": 0,
                                    "PRICE": 590,
                                    "PRINT_PRICE": "590₽",
                                    "CURRENCY": "RUB"
                                }
                            ],
                            "PRICE": 590,
                            "PRINT_PRICE": "590₽",
                            "ACTIONS": [
                                {
                                    "ID": 654738,
                                    "NAME": "Развивайся с нами ",
                                    "CODE": "razvivaysya_s_nami_",
                                    "COLOR": "#4B0082"
                                }
                            ]
                        },
                        {
                            "ID": "608911",
                            "NAME": "Книга \"45 татуировок продавана\". Правила для тех кто продаёт и управляет продажами | Комбат",
                            "DETAIL_PAGE_PATH": "/catalog/knigi_i_kanctovary/knigi/104353/",
                            "IMAGE": "https://img.stage.05.ru/resize/-iLRDuLKYzWN-SJx1VflNl-rOzWZgzFM5lKhxQo4N5o//rs:fit:1200:1722:0:0/q:100/bG9jYWw6Ly8vdXBsb2FkL2libG9jay9lNjMvZTYzNGQ1MGE5NTE3ZGM0Yzg4ODA0ZmU1MmFhM2MxZGIuanBn",
                            "THUMBNAILS": {
                                "1X": "https://img.stage.05.ru/resize/8kMIiVReSupD1XqysPQ-5QWQGcZ5umYNoF0FsGBu6d0//rs:fit:250:250:0:0/q:100/bG9jYWw6Ly8vdXBsb2FkL2libG9jay9lNjMvZTYzNGQ1MGE5NTE3ZGM0Yzg4ODA0ZmU1MmFhM2MxZGIuanBn",
                                "2X": "https://img.stage.05.ru/resize/Id_SyDU3TTyv4bL17t5hkupyMDTPXGCnivnbockwwqU//rs:fit:500:500:0:0/q:100/bG9jYWw6Ly8vdXBsb2FkL2libG9jay9lNjMvZTYzNGQ1MGE5NTE3ZGM0Yzg4ODA0ZmU1MmFhM2MxZGIuanBn"
                            },
                            "PRICES": [
                                {
                                    "CODE": "DEFAULT",
                                    "NAME": null,
                                    "CROSSED": false,
                                    "PRICE_TYPE_ID": 5,
                                    "BONUS": 0,
                                    "PRICE": 630,
                                    "PRINT_PRICE": "630₽",
                                    "CURRENCY": "RUB"
                                }
                            ],
                            "PRICE": 630,
                            "PRINT_PRICE": "630₽",
                            "ACTIONS": [
                                {
                                    "ID": 654738,
                                    "NAME": "Развивайся с нами ",
                                    "CODE": "razvivaysya_s_nami_",
                                    "COLOR": "#4B0082"
                                }
                            ]
                        },
                        {
                            "ID": "608912",
                            "NAME": "Книга \"Жить по принципу 80/20\" | Ричард Кох",
                            "DETAIL_PAGE_PATH": "/catalog/knigi_i_kanctovary/knigi/104354/",
                            "IMAGE": "https://img.stage.05.ru/resize/0R-ijNNzDZ2y-tJmzzlrlcMLArHQIB-DkRssg9H2X6I//rs:fit:418:597:0:0/q:100/bG9jYWw6Ly8vdXBsb2FkL2libG9jay8yNTYvMjU2NGZhYzI2YmI4Yzk0ODUxMGE3MWRkOTBlYmU1NGIuanBn",
                            "THUMBNAILS": {
                                "1X": "https://img.stage.05.ru/resize/B_l-9CRExHz6xSnAyrigubp3q-l2DcMrLOKg3Bo8Ip0//rs:fit:250:250:0:0/q:100/bG9jYWw6Ly8vdXBsb2FkL2libG9jay8yNTYvMjU2NGZhYzI2YmI4Yzk0ODUxMGE3MWRkOTBlYmU1NGIuanBn",
                                "2X": "https://img.stage.05.ru/resize/GBk4Ez4VsXJLTyR2qXPtG9wJfQoUfD4pbgmX57PVPug//rs:fit:500:500:0:0/q:100/bG9jYWw6Ly8vdXBsb2FkL2libG9jay8yNTYvMjU2NGZhYzI2YmI4Yzk0ODUxMGE3MWRkOTBlYmU1NGIuanBn"
                            },
                            "PRICES": [
                                {
                                    "CODE": "DEFAULT",
                                    "NAME": null,
                                    "CROSSED": false,
                                    "PRICE_TYPE_ID": 5,
                                    "BONUS": 0,
                                    "PRICE": 550,
                                    "PRINT_PRICE": "550₽",
                                    "CURRENCY": "RUB"
                                }
                            ],
                            "PRICE": 550,
                            "PRINT_PRICE": "550₽",
                            "ACTIONS": [
                                {
                                    "ID": 654738,
                                    "NAME": "Развивайся с нами ",
                                    "CODE": "razvivaysya_s_nami_",
                                    "COLOR": "#4B0082"
                                }
                            ]
                        },
                        {
                            "ID": "608914",
                            "NAME": "Книга \"45 татуировок менеджера\" | Комбат",
                            "DETAIL_PAGE_PATH": "/catalog/knigi_i_kanctovary/knigi/104357/",
                            "IMAGE": "https://img.stage.05.ru/resize/ak6DcmV0cqiBrnBvlqRJ4UclQIOEV6qMhPQq6_r-L0g//rs:fit:1051:1500:0:0/q:100/bG9jYWw6Ly8vdXBsb2FkL2libG9jay80ZTQvNGU0ZTdjODk3NTQ0OTQ4MWFlMjU1MTkzZDE1M2UwY2IuanBn",
                            "THUMBNAILS": {
                                "1X": "https://img.stage.05.ru/resize/1XUUWdT3ELu6kC_zb6vZbZ5xLk3HMv7dxeu9RYwvqGE//rs:fit:250:250:0:0/q:100/bG9jYWw6Ly8vdXBsb2FkL2libG9jay80ZTQvNGU0ZTdjODk3NTQ0OTQ4MWFlMjU1MTkzZDE1M2UwY2IuanBn",
                                "2X": "https://img.stage.05.ru/resize/9OlbMJQDAewYQ7z_7zUGC3u6mJf9u6XP1r4dfwNRSaI//rs:fit:500:500:0:0/q:100/bG9jYWw6Ly8vdXBsb2FkL2libG9jay80ZTQvNGU0ZTdjODk3NTQ0OTQ4MWFlMjU1MTkzZDE1M2UwY2IuanBn"
                            },
                            "PRICES": [
                                {
                                    "CODE": "DEFAULT",
                                    "NAME": null,
                                    "CROSSED": false,
                                    "PRICE_TYPE_ID": 5,
                                    "BONUS": 0,
                                    "PRICE": 630,
                                    "PRINT_PRICE": "630₽",
                                    "CURRENCY": "RUB"
                                }
                            ],
                            "PRICE": 630,
                            "PRINT_PRICE": "630₽",
                            "ACTIONS": [
                                {
                                    "ID": 654738,
                                    "NAME": "Развивайся с нами ",
                                    "CODE": "razvivaysya_s_nami_",
                                    "COLOR": "#4B0082"
                                }
                            ]
                        },
                        {
                            "ID": "608920",
                            "NAME": "Книга \"Бизнесхак на каждый день\" | Игорь Манн, Ренат Шагабутдинов ",
                            "DETAIL_PAGE_PATH": "/catalog/knigi_i_kanctovary/knigi/104368/",
                            "IMAGE": "https://img.stage.05.ru/resize/eZO7D7N73ZtN2urAeW9wpINB2LTxFtWpZz2iZdbBJ00//rs:fit:844:1080:0:0/q:100/bG9jYWw6Ly8vdXBsb2FkL2libG9jay8yYzcvMmM3MmMyOWVlOTM0OWM2M2JlMzFiNDY1NzhmODhiYzYuanBn",
                            "THUMBNAILS": {
                                "1X": "https://img.stage.05.ru/resize/UW-MX8MXskMBe0-dVg6uCsCTHwCfITey7768cxAQcdg//rs:fit:250:250:0:0/q:100/bG9jYWw6Ly8vdXBsb2FkL2libG9jay8yYzcvMmM3MmMyOWVlOTM0OWM2M2JlMzFiNDY1NzhmODhiYzYuanBn",
                                "2X": "https://img.stage.05.ru/resize/VgmHAYwZWsAgfCNYNqldL-I9D7fsqNCo_npqDmPtLBg//rs:fit:500:500:0:0/q:100/bG9jYWw6Ly8vdXBsb2FkL2libG9jay8yYzcvMmM3MmMyOWVlOTM0OWM2M2JlMzFiNDY1NzhmODhiYzYuanBn"
                            },
                            "PRICES": [
                                {
                                    "CODE": "DEFAULT",
                                    "NAME": null,
                                    "CROSSED": false,
                                    "PRICE_TYPE_ID": 5,
                                    "BONUS": 0,
                                    "PRICE": 580,
                                    "PRINT_PRICE": "580₽",
                                    "CURRENCY": "RUB"
                                },
                                {
                                    "CODE": "PROMO",
                                    "NAME": null,
                                    "CROSSED": true,
                                    "PRICE_TYPE_ID": 9,
                                    "BONUS": 0,
                                    "PRICE": 630,
                                    "PRINT_PRICE": "630₽",
                                    "CURRENCY": "RUB"
                                }
                            ],
                            "PRICE": 630,
                            "PRINT_PRICE": "630₽",
                            "ACTIONS": [
                                {
                                    "ID": 654738,
                                    "NAME": "Развивайся с нами ",
                                    "CODE": "razvivaysya_s_nami_",
                                    "COLOR": "#4B0082"
                                }
                            ]
                        },
                        {
                            "ID": "608921",
                            "NAME": "Книга \"Дело не в кофе: Корпоративная культура Starbucks\" | Говард Бехар",
                            "DETAIL_PAGE_PATH": "/catalog/knigi_i_kanctovary/knigi/104372/",
                            "IMAGE": "https://img.stage.05.ru/resize/dNnX4nExg_Q11c9KZXCerTl2gXNLqcAAI30XQHR4zis//rs:fit:486:722:0:0/q:100/bG9jYWw6Ly8vdXBsb2FkL2libG9jay9lNDIvZTQyY2NlNTFhZWQ0ZDE3OGMwOTI1MGQxMTBiNjI2NDUuanBn",
                            "THUMBNAILS": {
                                "1X": "https://img.stage.05.ru/resize/PeAoECJV_b_L8Wjk-QKfqtk6lLvkpz5dUy_2hAqTmr4//rs:fit:250:250:0:0/q:100/bG9jYWw6Ly8vdXBsb2FkL2libG9jay9lNDIvZTQyY2NlNTFhZWQ0ZDE3OGMwOTI1MGQxMTBiNjI2NDUuanBn",
                                "2X": "https://img.stage.05.ru/resize/Y2wZ_na17eLq8orxogQB7Kl5uvUNe51AXaNRmsuzuAk//rs:fit:500:500:0:0/q:100/bG9jYWw6Ly8vdXBsb2FkL2libG9jay9lNDIvZTQyY2NlNTFhZWQ0ZDE3OGMwOTI1MGQxMTBiNjI2NDUuanBn"
                            },
                            "PRICES": [
                                {
                                    "CODE": "DEFAULT",
                                    "NAME": null,
                                    "CROSSED": false,
                                    "PRICE_TYPE_ID": 5,
                                    "BONUS": 0,
                                    "PRICE": 525,
                                    "PRINT_PRICE": "525₽",
                                    "CURRENCY": "RUB"
                                }
                            ],
                            "PRICE": 525,
                            "PRINT_PRICE": "525₽",
                            "ACTIONS": [
                                {
                                    "ID": 654738,
                                    "NAME": "Развивайся с нами ",
                                    "CODE": "razvivaysya_s_nami_",
                                    "COLOR": "#4B0082"
                                }
                            ]
                        },
                        {
                            "ID": "608922",
                            "NAME": "Книга \"45 татуировок личности\" | Комбат",
                            "DETAIL_PAGE_PATH": "/catalog/knigi_i_kanctovary/knigi/104373/",
                            "IMAGE": "https://img.stage.05.ru/resize/AAwNLFjzKlfb2tEcf75hsTPDQfXVkfdM2KZ1-axgbNY//rs:fit:1200:1711:0:0/q:100/bG9jYWw6Ly8vdXBsb2FkL2libG9jay81ZDQvNWQ0ZGJkZGM3NGM0ZjliZDAxZmZjYTE1NjBhMTFkZDguanBn",
                            "THUMBNAILS": {
                                "1X": "https://img.stage.05.ru/resize/75TypEHrgh8ihycJO3uwb9_nyT_Mnpp-YJCNxclmMMs//rs:fit:250:250:0:0/q:100/bG9jYWw6Ly8vdXBsb2FkL2libG9jay81ZDQvNWQ0ZGJkZGM3NGM0ZjliZDAxZmZjYTE1NjBhMTFkZDguanBn",
                                "2X": "https://img.stage.05.ru/resize/2VcDUlaXq3sBIWRW42srHBy0lgFcsl5WvmAdVEFv3js//rs:fit:500:500:0:0/q:100/bG9jYWw6Ly8vdXBsb2FkL2libG9jay81ZDQvNWQ0ZGJkZGM3NGM0ZjliZDAxZmZjYTE1NjBhMTFkZDguanBn"
                            },
                            "PRICES": [
                                {
                                    "CODE": "DEFAULT",
                                    "NAME": null,
                                    "CROSSED": false,
                                    "PRICE_TYPE_ID": 5,
                                    "BONUS": 0,
                                    "PRICE": 630,
                                    "PRINT_PRICE": "630₽",
                                    "CURRENCY": "RUB"
                                }
                            ],
                            "PRICE": 630,
                            "PRINT_PRICE": "630₽",
                            "ACTIONS": [
                                {
                                    "ID": 654738,
                                    "NAME": "Развивайся с нами ",
                                    "CODE": "razvivaysya_s_nami_",
                                    "COLOR": "#4B0082"
                                }
                            ]
                        },
                        {
                            "ID": "609057",
                            "NAME": "Книга \"НЕ НОЙ\" | Джен Синсеро",
                            "DETAIL_PAGE_PATH": "/catalog/knigi_i_kanctovary/knigi/104359/",
                            "IMAGE": "https://img.stage.05.ru/resize/Z0eGwdQs72gJ3WJqlNnRjzipFzIKTKghUBrmw2UsVbY//rs:fit:798:1080:0:0/q:100/bG9jYWw6Ly8vdXBsb2FkL2libG9jay81OGEvNThhY2I0OTBhYzk0ODk4YjY5NjViN2IzNWViNGIwZWEuanBn",
                            "THUMBNAILS": {
                                "1X": "https://img.stage.05.ru/resize/nS-LTridDAg0_d2dWwBLGJVul1e9EBJUsQAnTJjOTD8//rs:fit:250:250:0:0/q:100/bG9jYWw6Ly8vdXBsb2FkL2libG9jay81OGEvNThhY2I0OTBhYzk0ODk4YjY5NjViN2IzNWViNGIwZWEuanBn",
                                "2X": "https://img.stage.05.ru/resize/8Di7ydo0RtfSNt2HQQqKpMedXGK_dLMT34fHjJ5MrRc//rs:fit:500:500:0:0/q:100/bG9jYWw6Ly8vdXBsb2FkL2libG9jay81OGEvNThhY2I0OTBhYzk0ODk4YjY5NjViN2IzNWViNGIwZWEuanBn"
                            },
                            "PRICES": [
                                {
                                    "CODE": "DEFAULT",
                                    "NAME": null,
                                    "CROSSED": false,
                                    "PRICE_TYPE_ID": 5,
                                    "BONUS": 0,
                                    "PRICE": 500,
                                    "PRINT_PRICE": "500₽",
                                    "CURRENCY": "RUB"
                                }
                            ],
                            "PRICE": 500,
                            "PRINT_PRICE": "500₽",
                            "ACTIONS": [
                                {
                                    "ID": 654738,
                                    "NAME": "Развивайся с нами ",
                                    "CODE": "razvivaysya_s_nami_",
                                    "COLOR": "#4B0082"
                                }
                            ]
                        },
                        {
                            "ID": "609058",
                            "NAME": "Книга \"Гении и аутсайдеры\" | Гладуэлл Малкольм",
                            "DETAIL_PAGE_PATH": "/catalog/knigi_i_kanctovary/knigi/104545/",
                            "IMAGE": "https://img.stage.05.ru/resize/dsBU1AscQmGPE_medgzKF1QGBNJiwAciYbBZU9285Os//rs:fit:1354:1920:0:0/q:100/bG9jYWw6Ly8vdXBsb2FkL2libG9jay9iOTUvYjk1OTA3YjNmY2U0NTg1NDk0NDc4ZWY0MDhmOTc3Y2MuanBn",
                            "THUMBNAILS": {
                                "1X": "https://img.stage.05.ru/resize/YVMPOWRRZ9cD_-BvRD2GNrBIUTihe4lbIfMk8RicTcM//rs:fit:250:250:0:0/q:100/bG9jYWw6Ly8vdXBsb2FkL2libG9jay9iOTUvYjk1OTA3YjNmY2U0NTg1NDk0NDc4ZWY0MDhmOTc3Y2MuanBn",
                                "2X": "https://img.stage.05.ru/resize/ZQBrgfUteJO5Tb1WMN3Yb-F1riCU9VqJ7J8NA__muzU//rs:fit:500:500:0:0/q:100/bG9jYWw6Ly8vdXBsb2FkL2libG9jay9iOTUvYjk1OTA3YjNmY2U0NTg1NDk0NDc4ZWY0MDhmOTc3Y2MuanBn"
                            },
                            "PRICES": [
                                {
                                    "CODE": "DEFAULT",
                                    "NAME": null,
                                    "CROSSED": false,
                                    "PRICE_TYPE_ID": 5,
                                    "BONUS": 0,
                                    "PRICE": 530,
                                    "PRINT_PRICE": "530₽",
                                    "CURRENCY": "RUB"
                                },
                                {
                                    "CODE": "PROMO",
                                    "NAME": null,
                                    "CROSSED": true,
                                    "PRICE_TYPE_ID": 9,
                                    "BONUS": 0,
                                    "PRICE": 580,
                                    "PRINT_PRICE": "580₽",
                                    "CURRENCY": "RUB"
                                }
                            ],
                            "PRICE": 580,
                            "PRINT_PRICE": "580₽",
                            "ACTIONS": [
                                {
                                    "ID": 654738,
                                    "NAME": "Развивайся с нами ",
                                    "CODE": "razvivaysya_s_nami_",
                                    "COLOR": "#4B0082"
                                }
                            ]
                        },
                        {
                            "ID": "609108",
                            "NAME": "Книга \"НИ СЫ\" | Джен Синсеро",
                            "DETAIL_PAGE_PATH": "/catalog/knigi_i_kanctovary/knigi/104814/",
                            "IMAGE": "https://img.stage.05.ru/resize/cux1lzajB1sZZ3AQSBIpcQw_7fgLOGXXWthb4OYxODI//rs:fit:366:531:0:0/q:100/bG9jYWw6Ly8vdXBsb2FkL2libG9jay9lYmMvZWJjNDZhMGUzMDc3MmQxZjc1MGU3YTAwMDlkZmQzZjAuanBn",
                            "THUMBNAILS": {
                                "1X": "https://img.stage.05.ru/resize/_Q0D0MZoRQFTFHFXn2wpN7cNoSrP_m_AnXaRDDksaOk//rs:fit:250:250:0:0/q:100/bG9jYWw6Ly8vdXBsb2FkL2libG9jay9lYmMvZWJjNDZhMGUzMDc3MmQxZjc1MGU3YTAwMDlkZmQzZjAuanBn",
                                "2X": "https://img.stage.05.ru/resize/t1jLBWM4XBP8BEaWh8tp0-HbGsBHDw1rP8V9E94HLtE//rs:fit:500:500:0:0/q:100/bG9jYWw6Ly8vdXBsb2FkL2libG9jay9lYmMvZWJjNDZhMGUzMDc3MmQxZjc1MGU3YTAwMDlkZmQzZjAuanBn"
                            },
                            "PRICES": [
                                {
                                    "CODE": "DEFAULT",
                                    "NAME": null,
                                    "CROSSED": false,
                                    "PRICE_TYPE_ID": 5,
                                    "BONUS": 0,
                                    "PRICE": 500,
                                    "PRINT_PRICE": "500₽",
                                    "CURRENCY": "RUB"
                                }
                            ],
                            "PRICE": 500,
                            "PRINT_PRICE": "500₽",
                            "ACTIONS": [
                                {
                                    "ID": 654738,
                                    "NAME": "Развивайся с нами ",
                                    "CODE": "razvivaysya_s_nami_",
                                    "COLOR": "#4B0082"
                                }
                            ]
                        },
                        {
                            "ID": "609408",
                            "NAME": "Книга \"Я вижу, о чем вы думаете\" | Джо Наварро, Марвин Карлинс",
                            "DETAIL_PAGE_PATH": "/catalog/knigi_i_kanctovary/knigi/104951/",
                            "IMAGE": "https://img.stage.05.ru/resize/_MvYkgBOzcbVwFl5PKeacYh6TVMXNZJPVDWIOGaeUMs//rs:fit:373:595:0:0/q:100/bG9jYWw6Ly8vdXBsb2FkL2libG9jay80MmIvNDJiZTEzYzRiOTg2N2FhZmZiN2ZmMjNkMTJkYjc2NTEuanBn",
                            "THUMBNAILS": {
                                "1X": "https://img.stage.05.ru/resize/7sAdCOl7ZG5DR-33rTF1qYYSwqq8vPDk7vH_xdxQB5w//rs:fit:250:250:0:0/q:100/bG9jYWw6Ly8vdXBsb2FkL2libG9jay80MmIvNDJiZTEzYzRiOTg2N2FhZmZiN2ZmMjNkMTJkYjc2NTEuanBn",
                                "2X": "https://img.stage.05.ru/resize/l4f14pYJ7474_8z3t-vXr3rbpFTVRJEHOdI1cvpF_iU//rs:fit:500:500:0:0/q:100/bG9jYWw6Ly8vdXBsb2FkL2libG9jay80MmIvNDJiZTEzYzRiOTg2N2FhZmZiN2ZmMjNkMTJkYjc2NTEuanBn"
                            },
                            "PRICES": [
                                {
                                    "CODE": "DEFAULT",
                                    "NAME": null,
                                    "CROSSED": false,
                                    "PRICE_TYPE_ID": 5,
                                    "BONUS": 0,
                                    "PRICE": 490,
                                    "PRINT_PRICE": "490₽",
                                    "CURRENCY": "RUB"
                                }
                            ],
                            "PRICE": 490,
                            "PRINT_PRICE": "490₽",
                            "ACTIONS": [
                                {
                                    "ID": 654738,
                                    "NAME": "Развивайся с нами ",
                                    "CODE": "razvivaysya_s_nami_",
                                    "COLOR": "#4B0082"
                                }
                            ]
                        },
                        {
                            "ID": "609412",
                            "NAME": "Книга \"Самый богатый человек в Вавилоне\" | Джордж Клейсон",
                            "DETAIL_PAGE_PATH": "/catalog/knigi_i_kanctovary/knigi/104952/",
                            "IMAGE": "https://img.stage.05.ru/resize/rzyFCX1GDwpnUXKRghYIcmXCgKtkMXz7r7enQA2p-WU//rs:fit:433:700:0:0/q:100/bG9jYWw6Ly8vdXBsb2FkL2libG9jay8zMmMvMzJjODAyNDg3NjIyNTE1NDYyMDgxMWRkNzNkODBmZDYuanBn",
                            "THUMBNAILS": {
                                "1X": "https://img.stage.05.ru/resize/9Jzn4unfSUEjrpgo9B9NYQINeHLmJBM7Ze66Dl2WIZI//rs:fit:250:250:0:0/q:100/bG9jYWw6Ly8vdXBsb2FkL2libG9jay8zMmMvMzJjODAyNDg3NjIyNTE1NDYyMDgxMWRkNzNkODBmZDYuanBn",
                                "2X": "https://img.stage.05.ru/resize/9Yg02OKzDPK8y1rn_7AyAdoNqGgX4ndmSPbv5OdhQTQ//rs:fit:500:500:0:0/q:100/bG9jYWw6Ly8vdXBsb2FkL2libG9jay8zMmMvMzJjODAyNDg3NjIyNTE1NDYyMDgxMWRkNzNkODBmZDYuanBn"
                            },
                            "PRICES": [
                                {
                                    "CODE": "DEFAULT",
                                    "NAME": null,
                                    "CROSSED": false,
                                    "PRICE_TYPE_ID": 5,
                                    "BONUS": 0,
                                    "PRICE": 450,
                                    "PRINT_PRICE": "450₽",
                                    "CURRENCY": "RUB"
                                }
                            ],
                            "PRICE": 450,
                            "PRINT_PRICE": "450₽",
                            "ACTIONS": [
                                {
                                    "ID": 654738,
                                    "NAME": "Развивайся с нами ",
                                    "CODE": "razvivaysya_s_nami_",
                                    "COLOR": "#4B0082"
                                }
                            ]
                        },
                        {
                            "ID": "610975",
                            "NAME": "Книга \"Зеленый король\" | Поль-Лу Сулицер",
                            "DETAIL_PAGE_PATH": "/catalog/knigi_i_kanctovary/knigi/106472/",
                            "IMAGE": "https://img.stage.05.ru/resize/9GXCdU80YJ7O4cqiSDQYrU1wJ_9hKeCJplj_KEtmNpQ//rs:fit:386:581:0:0/q:100/bG9jYWw6Ly8vdXBsb2FkL2libG9jay80ZDAvNGQwYWUzNzBlNmRkYjE2NWMxNjY5OTE5MWQzOGI0MzAuanBn",
                            "THUMBNAILS": {
                                "1X": "https://img.stage.05.ru/resize/hXVmcJN1RhJ2uy1bqA6L-BCYSZOuxbBqOYCIulSlCNc//rs:fit:250:250:0:0/q:100/bG9jYWw6Ly8vdXBsb2FkL2libG9jay80ZDAvNGQwYWUzNzBlNmRkYjE2NWMxNjY5OTE5MWQzOGI0MzAuanBn",
                                "2X": "https://img.stage.05.ru/resize/TlfVf_FYpvLerHLkVZ2Rl3np49D8j7bKEtPkSb_GlHM//rs:fit:500:500:0:0/q:100/bG9jYWw6Ly8vdXBsb2FkL2libG9jay80ZDAvNGQwYWUzNzBlNmRkYjE2NWMxNjY5OTE5MWQzOGI0MzAuanBn"
                            },
                            "PRICES": [
                                {
                                    "CODE": "DEFAULT",
                                    "NAME": null,
                                    "CROSSED": false,
                                    "PRICE_TYPE_ID": 5,
                                    "BONUS": 0,
                                    "PRICE": 550,
                                    "PRINT_PRICE": "550₽",
                                    "CURRENCY": "RUB"
                                }
                            ],
                            "PRICE": 550,
                            "PRINT_PRICE": "550₽",
                            "ACTIONS": [
                                {
                                    "ID": 654738,
                                    "NAME": "Развивайся с нами ",
                                    "CODE": "razvivaysya_s_nami_",
                                    "COLOR": "#4B0082"
                                }
                            ]
                        }
                    ]
                }
            ],
            "BASKET_AMOUNT": 0,
            "REVIEWS_BLOCK": {
                "PAGINATION": {
                    "PARAM": "page",
                    "COUNT": 0,
                    "CURRENT": 1,
                    "ROWS": 0
                },
                "ITEMS": null
            },
            "REVIEWS": null,
            "QUESTIONS_BLOCK": {
                "PAGINATION": {
                    "PARAM": "page",
                    "COUNT": 0,
                    "CURRENT": 1,
                    "ROWS": 0
                },
                "ITEMS": null
            },
            "QUESTIONS": null,
            "RATING": 0,
            "REVIEWS_COUNT": 0,
            "QUESTIONS_COUNT": 0
        }
    }
}